{
  "vtex.menu@2.x:menu#websites": {
    "children": [
      "menu-item#contact-us",
      "menu-item#about-us"
    ]
  },
  "vtex.menu@2.x:menu#institutional": {
    "children": [
      "menu-item#vtex-website"     
    ]
  },
  "menu-item#vtex-website": {
    "props": {
      "id": "menu-item-vtex-website",
      "type": "custom",
      "iconId": null,
      "highlight": false,
      "itemProps": {
        "type": "external",
        "href": "http://vtex.com",
        "noFollow": false,
        "tagTitle": "Powered by Vtex",
        "text": "Powered by Vtex"
      }
    }
  }
}
